[
  {
    "commodityCode": 401,
    "countryCode": 5700,
    "weeklyExports": 0,
    "accumulatedExports": 0,
    "outstandingSales": 13379,
    "grossNewSales": 13379,
    "currentMYNetSales": 0,
    "currentMYTotalCommitment": 13379,
    "nextMYOutstandingSales": 0,
    "nextMYNetSales": 0,
    "unitId": 1,
    "weekEndingDate": "2024-09-05T00:00:00"
  },
  {
    "commodityCode": 401,
    "countryCode": 5700,
    "weeklyExports": 0,
    "accumulatedExports": 0,
    "outstandingSales": 13379,
    "grossNewSales": 0,
    "currentMYNetSales": 0,
    "currentMYTotalCommitment": 13379,
    "nextMYOutstandingSales": 0,
    "nextMYNetSales": 0,
    "unitId": 1,
    "weekEndingDate": "2024-09-12T00:00:00"
  },
  {
    "commodityCode": 401,
    "countryCode": 5700,
    "weeklyExports": 3719,
    "accumulatedExports": 3719,
    "outstandingSales": 2650,
    "grossNewSales": 390,
    "currentMYNetSales": -7010,
    "currentMYTotalCommitment": 6369,
    "nextMYOutstandingSales": 0,
    "nextMYNetSales": 0,
    "unitId": 1,
    "weekEndingDate": "2024-09-19T00:00:00"
  },
  {
    "commodityCode": 401,
    "countryCode": 5700,
    "weeklyExports": 0,
    "accumulatedExports": 3719,
    "outstandingSales": 2650,
    "grossNewSales": 0,
    "currentMYNetSales": 0,
    "currentMYTotalCommitment": 6369,
    "nextMYOutstandingSales": 0,
    "nextMYNetSales": 0,
    "unitId": 1,
    "weekEndingDate": "2024-09-26T00:00:00"
  },
  {
    "commodityCode": 401,
    "countryCode": 5700,
    "weeklyExports": 2650,
    "accumulatedExports": 6369,
    "outstandingSales": 0,
    "grossNewSales": 0,
    "currentMYNetSales": 0,
    "currentMYTotalCommitment": 6369,
    "nextMYOutstandingSales": 0,
    "nextMYNetSales": 0,
    "unitId": 1,
    "weekEndingDate": "2024-10-03T00:00:00"
  },
  {
    "commodityCode": 401,
    "countryCode": 5700,
    "weeklyExports": 0,
    "accumulatedExports": 6369,
    "outstandingSales": 0,
    "grossNewSales": 0,
    "currentMYNetSales": 0,
    "currentMYTotalCommitment": 6369,
    "nextMYOutstandingSales": 0,
    "nextMYNetSales": 0,
    "unitId": 1,
    "weekEndingDate": "2024-10-10T00:00:00"
  },
  {
    "commodityCode": 401,
    "countryCode": 5700,
    "weeklyExports": 0,
    "accumulatedExports": 6369,
    "outstandingSales": 10000,
    "grossNewSales": 10000,
    "currentMYNetSales": 10000,
    "currentMYTotalCommitment": 16369,
    "nextMYOutstandingSales": 0,
    "nextMYNetSales": 0,
    "unitId": 1,
    "weekEndingDate": "2024-10-17T00:00:00"
  },
  {
    "commodityCode": 401,
    "countryCode": 5700,
    "weeklyExports": 0,
    "accumulatedExports": 6369,
    "outstandingSales": 10000,
    "grossNewSales": 0,
    "currentMYNetSales": 0,
    "currentMYTotalCommitment": 16369,
    "nextMYOutstandingSales": 0,
    "nextMYNetSales": 0,
    "unitId": 1,
    "weekEndingDate": "2024-10-24T00:00:00"
  },
  {
    "commodityCode": 401,
    "countryCode": 5700,
    "weeklyExports": 0,
    "accumulatedExports": 6369,
    "outstandingSales": 19000,
    "grossNewSales": 9000,
    "currentMYNetSales": 9000,
    "currentMYTotalCommitment": 25369,
    "nextMYOutstandingSales": 0,
    "nextMYNetSales": 0,
    "unitId": 1,
    "weekEndingDate": "2024-10-31T00:00:00"
  },
  {
    "commodityCode": 401,
    "countryCode": 5700,
    "weeklyExports": 4000,
    "accumulatedExports": 10369,
    "outstandingSales": 15000,
    "grossNewSales": 0,
    "currentMYNetSales": 0,
    "currentMYTotalCommitment": 25369,
    "nextMYOutstandingSales": 0,
    "nextMYNetSales": 0,
    "unitId": 1,
    "weekEndingDate": "2024-11-07T00:00:00"
  },
  {
    "commodityCode": 401,
    "countryCode": 5700,
    "weeklyExports": 0,
    "accumulatedExports": 10369,
    "outstandingSales": 15491,
    "grossNewSales": 491,
    "currentMYNetSales": 491,
    "currentMYTotalCommitment": 25860,
    "nextMYOutstandingSales": 0,
    "nextMYNetSales": 0,
    "unitId": 1,
    "weekEndingDate": "2024-11-14T00:00:00"
  },
  {
    "commodityCode": 401,
    "countryCode": 5700,
    "weeklyExports": 5491,
    "accumulatedExports": 15860,
    "outstandingSales": 10465,
    "grossNewSales": 465,
    "currentMYNetSales": 465,
    "currentMYTotalCommitment": 26325,
    "nextMYOutstandingSales": 0,
    "nextMYNetSales": 0,
    "unitId": 1,
    "weekEndingDate": "2024-11-21T00:00:00"
  },
  {
    "commodityCode": 401,
    "countryCode": 5700,
    "weeklyExports": 465,
    "accumulatedExports": 16325,
    "outstandingSales": 10000,
    "grossNewSales": 0,
    "currentMYNetSales": 0,
    "currentMYTotalCommitment": 26325,
    "nextMYOutstandingSales": 0,
    "nextMYNetSales": 0,
    "unitId": 1,
    "weekEndingDate": "2024-11-28T00:00:00"
  },
  {
    "commodityCode": 401,
    "countryCode": 5700,
    "weeklyExports": 0,
    "accumulatedExports": 16325,
    "outstandingSales": 10000,
    "grossNewSales": 0,
    "currentMYNetSales": 0,
    "currentMYTotalCommitment": 26325,
    "nextMYOutstandingSales": 0,
    "nextMYNetSales": 0,
    "unitId": 1,
    "weekEndingDate": "2024-12-05T00:00:00"
  },
  {
    "commodityCode": 401,
    "countryCode": 5700,
    "weeklyExports": 0,
    "accumulatedExports": 16325,
    "outstandingSales": 10000,
    "grossNewSales": 0,
    "currentMYNetSales": 0,
    "currentMYTotalCommitment": 26325,
    "nextMYOutstandingSales": 0,
    "nextMYNetSales": 0,
    "unitId": 1,
    "weekEndingDate": "2024-12-12T00:00:00"
  },
  {
    "commodityCode": 401,
    "countryCode": 5700,
    "weeklyExports": 0,
    "accumulatedExports": 16325,
    "outstandingSales": 10000,
    "grossNewSales": 0,
    "currentMYNetSales": 0,
    "currentMYTotalCommitment": 26325,
    "nextMYOutstandingSales": 0,
    "nextMYNetSales": 0,
    "unitId": 1,
    "weekEndingDate": "2024-12-19T00:00:00"
  },
  {
    "commodityCode": 401,
    "countryCode": 5700,
    "weeklyExports": 0,
    "accumulatedExports": 16325,
    "outstandingSales": 10000,
    "grossNewSales": 0,
    "currentMYNetSales": 0,
    "currentMYTotalCommitment": 26325,
    "nextMYOutstandingSales": 0,
    "nextMYNetSales": 0,
    "unitId": 1,
    "weekEndingDate": "2024-12-26T00:00:00"
  },
  {
    "commodityCode": 401,
    "countryCode": 5700,
    "weeklyExports": 3000,
    "accumulatedExports": 19325,
    "outstandingSales": 7000,
    "grossNewSales": 0,
    "currentMYNetSales": 0,
    "currentMYTotalCommitment": 26325,
    "nextMYOutstandingSales": 0,
    "nextMYNetSales": 0,
    "unitId": 1,
    "weekEndingDate": "2025-01-02T00:00:00"
  },
  {
    "commodityCode": 401,
    "countryCode": 5700,
    "weeklyExports": 3000,
    "accumulatedExports": 22325,
    "outstandingSales": 4000,
    "grossNewSales": 0,
    "currentMYNetSales": 0,
    "currentMYTotalCommitment": 26325,
    "nextMYOutstandingSales": 200,
    "nextMYNetSales": 200,
    "unitId": 1,
    "weekEndingDate": "2025-01-09T00:00:00"
  },
  {
    "commodityCode": 401,
    "countryCode": 5700,
    "weeklyExports": 0,
    "accumulatedExports": 22325,
    "outstandingSales": 10000,
    "grossNewSales": 6000,
    "currentMYNetSales": 6000,
    "currentMYTotalCommitment": 32325,
    "nextMYOutstandingSales": 400,
    "nextMYNetSales": 200,
    "unitId": 1,
    "weekEndingDate": "2025-01-16T00:00:00"
  },
  {
    "commodityCode": 401,
    "countryCode": 5700,
    "weeklyExports": 0,
    "accumulatedExports": 22325,
    "outstandingSales": 10000,
    "grossNewSales": 0,
    "currentMYNetSales": 0,
    "currentMYTotalCommitment": 32325,
    "nextMYOutstandingSales": 400,
    "nextMYNetSales": 0,
    "unitId": 1,
    "weekEndingDate": "2025-01-23T00:00:00"
  },
  {
    "commodityCode": 401,
    "countryCode": 5700,
    "weeklyExports": 6000,
    "accumulatedExports": 28325,
    "outstandingSales": 4000,
    "grossNewSales": 0,
    "currentMYNetSales": 0,
    "currentMYTotalCommitment": 32325,
    "nextMYOutstandingSales": 400,
    "nextMYNetSales": 0,
    "unitId": 1,
    "weekEndingDate": "2025-01-30T00:00:00"
  },
  {
    "commodityCode": 401,
    "countryCode": 5700,
    "weeklyExports": 0,
    "accumulatedExports": 28325,
    "outstandingSales": 4000,
    "grossNewSales": 0,
    "currentMYNetSales": 0,
    "currentMYTotalCommitment": 32325,
    "nextMYOutstandingSales": 400,
    "nextMYNetSales": 0,
    "unitId": 1,
    "weekEndingDate": "2025-02-06T00:00:00"
  },
  {
    "commodityCode": 401,
    "countryCode": 5700,
    "weeklyExports": 4000,
    "accumulatedExports": 32325,
    "outstandingSales": 0,
    "grossNewSales": 0,
    "currentMYNetSales": 0,
    "currentMYTotalCommitment": 32325,
    "nextMYOutstandingSales": 400,
    "nextMYNetSales": 0,
    "unitId": 1,
    "weekEndingDate": "2025-02-13T00:00:00"
  },
  {
    "commodityCode": 401,
    "countryCode": 5700,
    "weeklyExports": 0,
    "accumulatedExports": 32325,
    "outstandingSales": 0,
    "grossNewSales": 0,
    "currentMYNetSales": 0,
    "currentMYTotalCommitment": 32325,
    "nextMYOutstandingSales": 400,
    "nextMYNetSales": 0,
    "unitId": 1,
    "weekEndingDate": "2025-02-20T00:00:00"
  },
  {
    "commodityCode": 401,
    "countryCode": 5700,
    "weeklyExports": 0,
    "accumulatedExports": 32325,
    "outstandingSales": 0,
    "grossNewSales": 0,
    "currentMYNetSales": 0,
    "currentMYTotalCommitment": 32325,
    "nextMYOutstandingSales": 400,
    "nextMYNetSales": 0,
    "unitId": 1,
    "weekEndingDate": "2025-02-27T00:00:00"
  },
  {
    "commodityCode": 401,
    "countryCode": 5700,
    "weeklyExports": 0,
    "accumulatedExports": 32325,
    "outstandingSales": 0,
    "grossNewSales": 0,
    "currentMYNetSales": 0,
    "currentMYTotalCommitment": 32325,
    "nextMYOutstandingSales": 400,
    "nextMYNetSales": 0,
    "unitId": 1,
    "weekEndingDate": "2025-03-06T00:00:00"
  },
  {
    "commodityCode": 401,
    "countryCode": 5700,
    "weeklyExports": 209,
    "accumulatedExports": 32534,
    "outstandingSales": 191,
    "grossNewSales": 400,
    "currentMYNetSales": 400,
    "currentMYTotalCommitment": 32725,
    "nextMYOutstandingSales": 0,
    "nextMYNetSales": -400,
    "unitId": 1,
    "weekEndingDate": "2025-03-13T00:00:00"
  },
  {
    "commodityCode": 401,
    "countryCode": 5700,
    "weeklyExports": 90,
    "accumulatedExports": 32624,
    "outstandingSales": 101,
    "grossNewSales": 0,
    "currentMYNetSales": 0,
    "currentMYTotalCommitment": 32725,
    "nextMYOutstandingSales": 0,
    "nextMYNetSales": 0,
    "unitId": 1,
    "weekEndingDate": "2025-03-20T00:00:00"
  },
  {
    "commodityCode": 401,
    "countryCode": 5700,
    "weeklyExports": 0,
    "accumulatedExports": 32624,
    "outstandingSales": 101,
    "grossNewSales": 0,
    "currentMYNetSales": 0,
    "currentMYTotalCommitment": 32725,
    "nextMYOutstandingSales": 0,
    "nextMYNetSales": 0,
    "unitId": 1,
    "weekEndingDate": "2025-03-27T00:00:00"
  },
  {
    "commodityCode": 401,
    "countryCode": 5700,
    "weeklyExports": 0,
    "accumulatedExports": 32624,
    "outstandingSales": 100,
    "grossNewSales": 0,
    "currentMYNetSales": -1,
    "currentMYTotalCommitment": 32724,
    "nextMYOutstandingSales": 0,
    "nextMYNetSales": 0,
    "unitId": 1,
    "weekEndingDate": "2025-04-03T00:00:00"
  },
  {
    "commodityCode": 401,
    "countryCode": 5700,
    "weeklyExports": 0,
    "accumulatedExports": 32624,
    "outstandingSales": 100,
    "grossNewSales": 0,
    "currentMYNetSales": 0,
    "currentMYTotalCommitment": 32724,
    "nextMYOutstandingSales": 0,
    "nextMYNetSales": 0,
    "unitId": 1,
    "weekEndingDate": "2025-04-10T00:00:00"
  },
  {
    "commodityCode": 401,
    "countryCode": 5700,
    "weeklyExports": 100,
    "accumulatedExports": 32724,
    "outstandingSales": 0,
    "grossNewSales": 0,
    "currentMYNetSales": 0,
    "currentMYTotalCommitment": 32724,
    "nextMYOutstandingSales": 0,
    "nextMYNetSales": 0,
    "unitId": 1,
    "weekEndingDate": "2025-04-17T00:00:00"
  },
  {
    "commodityCode": 401,
    "countryCode": 5700,
    "weeklyExports": 0,
    "accumulatedExports": 32724,
    "outstandingSales": 0,
    "grossNewSales": 0,
    "currentMYNetSales": 0,
    "currentMYTotalCommitment": 32724,
    "nextMYOutstandingSales": 0,
    "nextMYNetSales": 0,
    "unitId": 1,
    "weekEndingDate": "2025-04-24T00:00:00"
  },
  {
    "commodityCode": 401,
    "countryCode": 5700,
    "weeklyExports": 0,
    "accumulatedExports": 32724,
    "outstandingSales": 0,
    "grossNewSales": 0,
    "currentMYNetSales": 0,
    "currentMYTotalCommitment": 32724,
    "nextMYOutstandingSales": 0,
    "nextMYNetSales": 0,
    "unitId": 1,
    "weekEndingDate": "2025-05-01T00:00:00"
  },
  {
    "commodityCode": 401,
    "countryCode": 5700,
    "weeklyExports": 0,
    "accumulatedExports": 32724,
    "outstandingSales": 0,
    "grossNewSales": 0,
    "currentMYNetSales": 0,
    "currentMYTotalCommitment": 32724,
    "nextMYOutstandingSales": 0,
    "nextMYNetSales": 0,
    "unitId": 1,
    "weekEndingDate": "2025-05-08T00:00:00"
  },
  {
    "commodityCode": 401,
    "countryCode": 5700,
    "weeklyExports": 0,
    "accumulatedExports": 32724,
    "outstandingSales": 0,
    "grossNewSales": 0,
    "currentMYNetSales": 0,
    "currentMYTotalCommitment": 32724,
    "nextMYOutstandingSales": 0,
    "nextMYNetSales": 0,
    "unitId": 1,
    "weekEndingDate": "2025-05-15T00:00:00"
  },
  {
    "commodityCode": 401,
    "countryCode": 5700,
    "weeklyExports": 0,
    "accumulatedExports": 32724,
    "outstandingSales": 0,
    "grossNewSales": 0,
    "currentMYNetSales": 0,
    "currentMYTotalCommitment": 32724,
    "nextMYOutstandingSales": 0,
    "nextMYNetSales": 0,
    "unitId": 1,
    "weekEndingDate": "2025-05-22T00:00:00"
  },
  {
    "commodityCode": 401,
    "countryCode": 5700,
    "weeklyExports": 0,
    "accumulatedExports": 32724,
    "outstandingSales": 0,
    "grossNewSales": 0,
    "currentMYNetSales": 0,
    "currentMYTotalCommitment": 32724,
    "nextMYOutstandingSales": 0,
    "nextMYNetSales": 0,
    "unitId": 1,
    "weekEndingDate": "2025-05-29T00:00:00"
  },
  {
    "commodityCode": 401,
    "countryCode": 5700,
    "weeklyExports": 0,
    "accumulatedExports": 32724,
    "outstandingSales": 0,
    "grossNewSales": 0,
    "currentMYNetSales": 0,
    "currentMYTotalCommitment": 32724,
    "nextMYOutstandingSales": 0,
    "nextMYNetSales": 0,
    "unitId": 1,
    "weekEndingDate": "2025-06-05T00:00:00"
  },
  {
    "commodityCode": 401,
    "countryCode": 5700,
    "weeklyExports": 0,
    "accumulatedExports": 32724,
    "outstandingSales": 0,
    "grossNewSales": 0,
    "currentMYNetSales": 0,
    "currentMYTotalCommitment": 32724,
    "nextMYOutstandingSales": 0,
    "nextMYNetSales": 0,
    "unitId": 1,
    "weekEndingDate": "2025-06-12T00:00:00"
  },
  {
    "commodityCode": 401,
    "countryCode": 5700,
    "weeklyExports": 0,
    "accumulatedExports": 32724,
    "outstandingSales": 0,
    "grossNewSales": 0,
    "currentMYNetSales": 0,
    "currentMYTotalCommitment": 32724,
    "nextMYOutstandingSales": 0,
    "nextMYNetSales": 0,
    "unitId": 1,
    "weekEndingDate": "2025-06-19T00:00:00"
  },
  {
    "commodityCode": 401,
    "countryCode": 5700,
    "weeklyExports": 0,
    "accumulatedExports": 32724,
    "outstandingSales": 0,
    "grossNewSales": 0,
    "currentMYNetSales": 0,
    "currentMYTotalCommitment": 32724,
    "nextMYOutstandingSales": 0,
    "nextMYNetSales": 0,
    "unitId": 1,
    "weekEndingDate": "2025-06-26T00:00:00"
  },
  {
    "commodityCode": 401,
    "countryCode": 5700,
    "weeklyExports": 0,
    "accumulatedExports": 32724,
    "outstandingSales": 0,
    "grossNewSales": 0,
    "currentMYNetSales": 0,
    "currentMYTotalCommitment": 32724,
    "nextMYOutstandingSales": 0,
    "nextMYNetSales": 0,
    "unitId": 1,
    "weekEndingDate": "2025-07-03T00:00:00"
  },
  {
    "commodityCode": 401,
    "countryCode": 5700,
    "weeklyExports": 0,
    "accumulatedExports": 32724,
    "outstandingSales": 0,
    "grossNewSales": 0,
    "currentMYNetSales": 0,
    "currentMYTotalCommitment": 32724,
    "nextMYOutstandingSales": 0,
    "nextMYNetSales": 0,
    "unitId": 1,
    "weekEndingDate": "2025-07-10T00:00:00"
  },
  {
    "commodityCode": 401,
    "countryCode": 5700,
    "weeklyExports": 0,
    "accumulatedExports": 32724,
    "outstandingSales": 0,
    "grossNewSales": 0,
    "currentMYNetSales": 0,
    "currentMYTotalCommitment": 32724,
    "nextMYOutstandingSales": 0,
    "nextMYNetSales": 0,
    "unitId": 1,
    "weekEndingDate": "2025-07-17T00:00:00"
  },
  {
    "commodityCode": 401,
    "countryCode": 5700,
    "weeklyExports": 0,
    "accumulatedExports": 32724,
    "outstandingSales": 0,
    "grossNewSales": 0,
    "currentMYNetSales": 0,
    "currentMYTotalCommitment": 32724,
    "nextMYOutstandingSales": 0,
    "nextMYNetSales": 0,
    "unitId": 1,
    "weekEndingDate": "2025-07-24T00:00:00"
  },
  {
    "commodityCode": 401,
    "countryCode": 5700,
    "weeklyExports": 0,
    "accumulatedExports": 32724,
    "outstandingSales": 0,
    "grossNewSales": 0,
    "currentMYNetSales": 0,
    "currentMYTotalCommitment": 32724,
    "nextMYOutstandingSales": 0,
    "nextMYNetSales": 0,
    "unitId": 1,
    "weekEndingDate": "2025-07-31T00:00:00"
  },
  {
    "commodityCode": 401,
    "countryCode": 5700,
    "weeklyExports": 0,
    "accumulatedExports": 32724,
    "outstandingSales": 0,
    "grossNewSales": 0,
    "currentMYNetSales": 0,
    "currentMYTotalCommitment": 32724,
    "nextMYOutstandingSales": 0,
    "nextMYNetSales": 0,
    "unitId": 1,
    "weekEndingDate": "2025-08-07T00:00:00"
  },
  {
    "commodityCode": 401,
    "countryCode": 5700,
    "weeklyExports": 0,
    "accumulatedExports": 32724,
    "outstandingSales": 0,
    "grossNewSales": 0,
    "currentMYNetSales": 0,
    "currentMYTotalCommitment": 32724,
    "nextMYOutstandingSales": 0,
    "nextMYNetSales": 0,
    "unitId": 1,
    "weekEndingDate": "2025-08-14T00:00:00"
  },
  {
    "commodityCode": 401,
    "countryCode": 5700,
    "weeklyExports": 0,
    "accumulatedExports": 32724,
    "outstandingSales": 0,
    "grossNewSales": 0,
    "currentMYNetSales": 0,
    "currentMYTotalCommitment": 32724,
    "nextMYOutstandingSales": 0,
    "nextMYNetSales": 0,
    "unitId": 1,
    "weekEndingDate": "2025-08-21T00:00:00"
  },
  {
    "commodityCode": 401,
    "countryCode": 5700,
    "weeklyExports": 0,
    "accumulatedExports": 32724,
    "outstandingSales": 0,
    "grossNewSales": 0,
    "currentMYNetSales": 0,
    "currentMYTotalCommitment": 32724,
    "nextMYOutstandingSales": 0,
    "nextMYNetSales": 0,
    "unitId": 1,
    "weekEndingDate": "2025-08-28T00:00:00"
  },
  {
    "commodityCode": 401,
    "countryCode": 5700,
    "weeklyExports": 0,
    "accumulatedExports": 32724,
    "outstandingSales": 0,
    "grossNewSales": 0,
    "currentMYNetSales": 0,
    "currentMYTotalCommitment": 32724,
    "nextMYOutstandingSales": 0,
    "nextMYNetSales": 0,
    "unitId": 1,
    "weekEndingDate": "2025-09-04T00:00:00"
  }
]