[
  {
    "commodityCode": 801,
    "countryCode": 2,
    "weeklyExports": 0,
    "accumulatedExports": 0,
    "outstandingSales": 5598868,
    "grossNewSales": 578000,
    "currentMYNetSales": -52334,
    "currentMYTotalCommitment": 5598868,
    "nextMYOutstandingSales": 0,
    "nextMYNetSales": 0,
    "unitId": 1,
    "weekEndingDate": "2017-09-07T00:00:00",
    "marketYear": 2018
  },
  {
    "commodityCode": 801,
    "countryCode": 2,
    "weeklyExports": 0,
    "accumulatedExports": 0,
    "outstandingSales": 6127668,
    "grossNewSales": 924800,
    "currentMYNetSales": 528800,
    "currentMYTotalCommitment": 6127668,
    "nextMYOutstandingSales": 0,
    "nextMYNetSales": 0,
    "unitId": 1,
    "weekEndingDate": "2017-09-14T00:00:00",
    "marketYear": 2018
  },
  {
    "commodityCode": 801,
    "countryCode": 2,
    "weeklyExports": 0,
    "accumulatedExports": 0,
    "outstandingSales": 7131668,
    "grossNewSales": 1416000,
    "currentMYNetSales": 1004000,
    "currentMYTotalCommitment": 7131668,
    "nextMYOutstandingSales": 120000,
    "nextMYNetSales": 120000,
    "unitId": 1,
    "weekEndingDate": "2017-09-21T00:00:00",
    "marketYear": 2018
  },
  {
    "commodityCode": 801,
    "countryCode": 2,
    "weeklyExports": 0,
    "accumulatedExports": 0,
    "outstandingSales": 7075168,
    "grossNewSales": 506500,
    "currentMYNetSales": -56500,
    "currentMYTotalCommitment": 7075168,
    "nextMYOutstandingSales": 120000,
    "nextMYNetSales": 0,
    "unitId": 1,
    "weekEndingDate": "2017-09-28T00:00:00",
    "marketYear": 2018
  },
  {
    "commodityCode": 801,
    "countryCode": 2,
    "weeklyExports": 0,
    "accumulatedExports": 0,
    "outstandingSales": 7426650,
    "grossNewSales": 868150,
    "currentMYNetSales": 351482,
    "currentMYTotalCommitment": 7426650,
    "nextMYOutstandingSales": 120000,
    "nextMYNetSales": 0,
    "unitId": 1,
    "weekEndingDate": "2017-10-05T00:00:00",
    "marketYear": 2018
  },
  {
    "commodityCode": 801,
    "countryCode": 2,
    "weeklyExports": 0,
    "accumulatedExports": 0,
    "outstandingSales": 7109250,
    "grossNewSales": 535600,
    "currentMYNetSales": -317400,
    "currentMYTotalCommitment": 7109250,
    "nextMYOutstandingSales": 120000,
    "nextMYNetSales": 0,
    "unitId": 1,
    "weekEndingDate": "2017-10-12T00:00:00",
    "marketYear": 2018
  },
  {
    "commodityCode": 801,
    "countryCode": 2,
    "weeklyExports": 0,
    "accumulatedExports": 0,
    "outstandingSales": 7119522,
    "grossNewSales": 799772,
    "currentMYNetSales": 10272,
    "currentMYTotalCommitment": 7119522,
    "nextMYOutstandingSales": 120000,
    "nextMYNetSales": 0,
    "unitId": 1,
    "weekEndingDate": "2017-10-19T00:00:00",
    "marketYear": 2018
  },
  {
    "commodityCode": 801,
    "countryCode": 2,
    "weeklyExports": 0,
    "accumulatedExports": 0,
    "outstandingSales": 6908500,
    "grossNewSales": 866000,
    "currentMYNetSales": -211022,
    "currentMYTotalCommitment": 6908500,
    "nextMYOutstandingSales": 120000,
    "nextMYNetSales": 0,
    "unitId": 1,
    "weekEndingDate": "2017-10-26T00:00:00",
    "marketYear": 2018
  },
  {
    "commodityCode": 801,
    "countryCode": 2,
    "weeklyExports": 0,
    "accumulatedExports": 0,
    "outstandingSales": 6201000,
    "grossNewSales": 306500,
    "currentMYNetSales": -707500,
    "currentMYTotalCommitment": 6201000,
    "nextMYOutstandingSales": 120000,
    "nextMYNetSales": 0,
    "unitId": 1,
    "weekEndingDate": "2017-11-02T00:00:00",
    "marketYear": 2018
  },
  {
    "commodityCode": 801,
    "countryCode": 2,
    "weeklyExports": 0,
    "accumulatedExports": 0,
    "outstandingSales": 5539000,
    "grossNewSales": 344000,
    "currentMYNetSales": -662000,
    "currentMYTotalCommitment": 5539000,
    "nextMYOutstandingSales": 192100,
    "nextMYNetSales": 72100,
    "unitId": 1,
    "weekEndingDate": "2017-11-09T00:00:00",
    "marketYear": 2018
  },
  {
    "commodityCode": 801,
    "countryCode": 2,
    "weeklyExports": 0,
    "accumulatedExports": 0,
    "outstandingSales": 5703000,
    "grossNewSales": 603500,
    "currentMYNetSales": 164000,
    "currentMYTotalCommitment": 5703000,
    "nextMYOutstandingSales": 192100,
    "nextMYNetSales": 0,
    "unitId": 1,
    "weekEndingDate": "2017-11-16T00:00:00",
    "marketYear": 2018
  },
  {
    "commodityCode": 801,
    "countryCode": 2,
    "weeklyExports": 0,
    "accumulatedExports": 0,
    "outstandingSales": 5581500,
    "grossNewSales": 480500,
    "currentMYNetSales": -121500,
    "currentMYTotalCommitment": 5581500,
    "nextMYOutstandingSales": 192100,
    "nextMYNetSales": 0,
    "unitId": 1,
    "weekEndingDate": "2017-11-23T00:00:00",
    "marketYear": 2018
  },
  {
    "commodityCode": 801,
    "countryCode": 2,
    "weeklyExports": 0,
    "accumulatedExports": 0,
    "outstandingSales": 5526900,
    "grossNewSales": 760900,
    "currentMYNetSales": -54600,
    "currentMYTotalCommitment": 5526900,
    "nextMYOutstandingSales": 258100,
    "nextMYNetSales": 66000,
    "unitId": 1,
    "weekEndingDate": "2017-11-30T00:00:00",
    "marketYear": 2018
  },
  {
    "commodityCode": 801,
    "countryCode": 2,
    "weeklyExports": 0,
    "accumulatedExports": 0,
    "outstandingSales": 5396700,
    "grossNewSales": 552500,
    "currentMYNetSales": -130200,
    "currentMYTotalCommitment": 5396700,
    "nextMYOutstandingSales": 369100,
    "nextMYNetSales": 111000,
    "unitId": 1,
    "weekEndingDate": "2017-12-07T00:00:00",
    "marketYear": 2018
  },
  {
    "commodityCode": 801,
    "countryCode": 2,
    "weeklyExports": 0,
    "accumulatedExports": 0,
    "outstandingSales": 5035946,
    "grossNewSales": 734300,
    "currentMYNetSales": -360754,
    "currentMYTotalCommitment": 5035946,
    "nextMYOutstandingSales": 389100,
    "nextMYNetSales": 20000,
    "unitId": 1,
    "weekEndingDate": "2017-12-14T00:00:00",
    "marketYear": 2018
  },
  {
    "commodityCode": 801,
    "countryCode": 2,
    "weeklyExports": 0,
    "accumulatedExports": 0,
    "outstandingSales": 4708496,
    "grossNewSales": 256700,
    "currentMYNetSales": -327450,
    "currentMYTotalCommitment": 4708496,
    "nextMYOutstandingSales": 462000,
    "nextMYNetSales": 72900,
    "unitId": 1,
    "weekEndingDate": "2017-12-21T00:00:00",
    "marketYear": 2018
  },
  {
    "commodityCode": 801,
    "countryCode": 2,
    "weeklyExports": 0,
    "accumulatedExports": 0,
    "outstandingSales": 4364850,
    "grossNewSales": 74900,
    "currentMYNetSales": -343646,
    "currentMYTotalCommitment": 4364850,
    "nextMYOutstandingSales": 462000,
    "nextMYNetSales": 0,
    "unitId": 1,
    "weekEndingDate": "2017-12-28T00:00:00",
    "marketYear": 2018
  },
  {
    "commodityCode": 801,
    "countryCode": 2,
    "weeklyExports": 0,
    "accumulatedExports": 0,
    "outstandingSales": 3871500,
    "grossNewSales": 192000,
    "currentMYNetSales": -493350,
    "currentMYTotalCommitment": 3871500,
    "nextMYOutstandingSales": 462000,
    "nextMYNetSales": 0,
    "unitId": 1,
    "weekEndingDate": "2018-01-04T00:00:00",
    "marketYear": 2018
  },
  {
    "commodityCode": 801,
    "countryCode": 2,
    "weeklyExports": 0,
    "accumulatedExports": 0,
    "outstandingSales": 3820088,
    "grossNewSales": 386588,
    "currentMYNetSales": -51412,
    "currentMYTotalCommitment": 3820088,
    "nextMYOutstandingSales": 723000,
    "nextMYNetSales": 261000,
    "unitId": 1,
    "weekEndingDate": "2018-01-11T00:00:00",
    "marketYear": 2018
  },
  {
    "commodityCode": 801,
    "countryCode": 2,
    "weeklyExports": 0,
    "accumulatedExports": 0,
    "outstandingSales": 3742093,
    "grossNewSales": 191463,
    "currentMYNetSales": -77995,
    "currentMYTotalCommitment": 3742093,
    "nextMYOutstandingSales": 853000,
    "nextMYNetSales": 130000,
    "unitId": 1,
    "weekEndingDate": "2018-01-18T00:00:00",
    "marketYear": 2018
  },
  {
    "commodityCode": 801,
    "countryCode": 2,
    "weeklyExports": 0,
    "accumulatedExports": 0,
    "outstandingSales": 3341782,
    "grossNewSales": 229764,
    "currentMYNetSales": -400311,
    "currentMYTotalCommitment": 3341782,
    "nextMYOutstandingSales": 903000,
    "nextMYNetSales": 50000,
    "unitId": 1,
    "weekEndingDate": "2018-01-25T00:00:00",
    "marketYear": 2018
  },
  {
    "commodityCode": 801,
    "countryCode": 2,
    "weeklyExports": 0,
    "accumulatedExports": 0,
    "outstandingSales": 3136056,
    "grossNewSales": 274150,
    "currentMYNetSales": -205726,
    "currentMYTotalCommitment": 3136056,
    "nextMYOutstandingSales": 903000,
    "nextMYNetSales": 0,
    "unitId": 1,
    "weekEndingDate": "2018-02-01T00:00:00",
    "marketYear": 2018
  },
  {
    "commodityCode": 801,
    "countryCode": 2,
    "weeklyExports": 0,
    "accumulatedExports": 0,
    "outstandingSales": 2976756,
    "grossNewSales": 357700,
    "currentMYNetSales": -159300,
    "currentMYTotalCommitment": 2976756,
    "nextMYOutstandingSales": 1100000,
    "nextMYNetSales": 197000,
    "unitId": 1,
    "weekEndingDate": "2018-02-08T00:00:00",
    "marketYear": 2018
  },
  {
    "commodityCode": 801,
    "countryCode": 2,
    "weeklyExports": 0,
    "accumulatedExports": 0,
    "outstandingSales": 2853580,
    "grossNewSales": 137000,
    "currentMYNetSales": -123176,
    "currentMYTotalCommitment": 2853580,
    "nextMYOutstandingSales": 1322000,
    "nextMYNetSales": 222000,
    "unitId": 1,
    "weekEndingDate": "2018-02-15T00:00:00",
    "marketYear": 2018
  },
  {
    "commodityCode": 801,
    "countryCode": 2,
    "weeklyExports": 0,
    "accumulatedExports": 0,
    "outstandingSales": 2831550,
    "grossNewSales": 181500,
    "currentMYNetSales": -22030,
    "currentMYTotalCommitment": 2831550,
    "nextMYOutstandingSales": 1443000,
    "nextMYNetSales": 121000,
    "unitId": 1,
    "weekEndingDate": "2018-02-22T00:00:00",
    "marketYear": 2018
  },
  {
    "commodityCode": 801,
    "countryCode": 2,
    "weeklyExports": 0,
    "accumulatedExports": 0,
    "outstandingSales": 3103550,
    "grossNewSales": 593000,
    "currentMYNetSales": 272000,
    "currentMYTotalCommitment": 3103550,
    "nextMYOutstandingSales": 1526000,
    "nextMYNetSales": 83000,
    "unitId": 1,
    "weekEndingDate": "2018-03-01T00:00:00",
    "marketYear": 2018
  },
  {
    "commodityCode": 801,
    "countryCode": 2,
    "weeklyExports": 0,
    "accumulatedExports": 0,
    "outstandingSales": 3314550,
    "grossNewSales": 479000,
    "currentMYNetSales": 211000,
    "currentMYTotalCommitment": 3314550,
    "nextMYOutstandingSales": 1589000,
    "nextMYNetSales": 63000,
    "unitId": 1,
    "weekEndingDate": "2018-03-08T00:00:00",
    "marketYear": 2018
  },
  {
    "commodityCode": 801,
    "countryCode": 2,
    "weeklyExports": 0,
    "accumulatedExports": 0,
    "outstandingSales": 3291850,
    "grossNewSales": 161000,
    "currentMYNetSales": -22700,
    "currentMYTotalCommitment": 3291850,
    "nextMYOutstandingSales": 1728500,
    "nextMYNetSales": 139500,
    "unitId": 1,
    "weekEndingDate": "2018-03-15T00:00:00",
    "marketYear": 2018
  },
  {
    "commodityCode": 801,
    "countryCode": 2,
    "weeklyExports": 0,
    "accumulatedExports": 0,
    "outstandingSales": 3047850,
    "grossNewSales": 67000,
    "currentMYNetSales": -244000,
    "currentMYTotalCommitment": 3047850,
    "nextMYOutstandingSales": 1728500,
    "nextMYNetSales": 0,
    "unitId": 1,
    "weekEndingDate": "2018-03-22T00:00:00",
    "marketYear": 2018
  },
  {
    "commodityCode": 801,
    "countryCode": 2,
    "weeklyExports": 0,
    "accumulatedExports": 0,
    "outstandingSales": 3658250,
    "grossNewSales": 854400,
    "currentMYNetSales": 610400,
    "currentMYTotalCommitment": 3658250,
    "nextMYOutstandingSales": 1819500,
    "nextMYNetSales": 91000,
    "unitId": 1,
    "weekEndingDate": "2018-03-29T00:00:00",
    "marketYear": 2018
  },
  {
    "commodityCode": 801,
    "countryCode": 2,
    "weeklyExports": 0,
    "accumulatedExports": 0,
    "outstandingSales": 4324000,
    "grossNewSales": 779000,
    "currentMYNetSales": 665750,
    "currentMYTotalCommitment": 4324000,
    "nextMYOutstandingSales": 2391500,
    "nextMYNetSales": 572000,
    "unitId": 1,
    "weekEndingDate": "2018-04-05T00:00:00",
    "marketYear": 2018
  },
  {
    "commodityCode": 801,
    "countryCode": 2,
    "weeklyExports": 0,
    "accumulatedExports": 0,
    "outstandingSales": 4905000,
    "grossNewSales": 642500,
    "currentMYNetSales": 581000,
    "currentMYTotalCommitment": 4905000,
    "nextMYOutstandingSales": 2579500,
    "nextMYNetSales": 188000,
    "unitId": 1,
    "weekEndingDate": "2018-04-12T00:00:00",
    "marketYear": 2018
  },
  {
    "commodityCode": 801,
    "countryCode": 2,
    "weeklyExports": 0,
    "accumulatedExports": 0,
    "outstandingSales": 4925500,
    "grossNewSales": 192000,
    "currentMYNetSales": 20500,
    "currentMYTotalCommitment": 4925500,
    "nextMYOutstandingSales": 2688500,
    "nextMYNetSales": 109000,
    "unitId": 1,
    "weekEndingDate": "2018-04-19T00:00:00",
    "marketYear": 2018
  },
  {
    "commodityCode": 801,
    "countryCode": 2,
    "weeklyExports": 0,
    "accumulatedExports": 0,
    "outstandingSales": 4920200,
    "grossNewSales": 100200,
    "currentMYNetSales": -5300,
    "currentMYTotalCommitment": 4920200,
    "nextMYOutstandingSales": 2817500,
    "nextMYNetSales": 129000,
    "unitId": 1,
    "weekEndingDate": "2018-04-26T00:00:00",
    "marketYear": 2018
  },
  {
    "commodityCode": 801,
    "countryCode": 2,
    "weeklyExports": 0,
    "accumulatedExports": 0,
    "outstandingSales": 4830200,
    "grossNewSales": 85000,
    "currentMYNetSales": -90000,
    "currentMYTotalCommitment": 4830200,
    "nextMYOutstandingSales": 3000500,
    "nextMYNetSales": 183000,
    "unitId": 1,
    "weekEndingDate": "2018-05-03T00:00:00",
    "marketYear": 2018
  },
  {
    "commodityCode": 801,
    "countryCode": 2,
    "weeklyExports": 0,
    "accumulatedExports": 0,
    "outstandingSales": 4605700,
    "grossNewSales": 10700,
    "currentMYNetSales": -224500,
    "currentMYTotalCommitment": 4605700,
    "nextMYOutstandingSales": 3060500,
    "nextMYNetSales": 60000,
    "unitId": 1,
    "weekEndingDate": "2018-05-10T00:00:00",
    "marketYear": 2018
  },
  {
    "commodityCode": 801,
    "countryCode": 2,
    "weeklyExports": 0,
    "accumulatedExports": 0,
    "outstandingSales": 3711200,
    "grossNewSales": 268700,
    "currentMYNetSales": -894500,
    "currentMYTotalCommitment": 3711200,
    "nextMYOutstandingSales": 3052500,
    "nextMYNetSales": -8000,
    "unitId": 1,
    "weekEndingDate": "2018-05-17T00:00:00",
    "marketYear": 2018
  },
  {
    "commodityCode": 801,
    "countryCode": 2,
    "weeklyExports": 0,
    "accumulatedExports": 0,
    "outstandingSales": 3614300,
    "grossNewSales": 69800,
    "currentMYNetSales": -96900,
    "currentMYTotalCommitment": 3614300,
    "nextMYOutstandingSales": 3382500,
    "nextMYNetSales": 330000,
    "unitId": 1,
    "weekEndingDate": "2018-05-24T00:00:00",
    "marketYear": 2018
  },
  {
    "commodityCode": 801,
    "countryCode": 2,
    "weeklyExports": 0,
    "accumulatedExports": 0,
    "outstandingSales": 3595300,
    "grossNewSales": 82000,
    "currentMYNetSales": -19000,
    "currentMYTotalCommitment": 3595300,
    "nextMYOutstandingSales": 3382500,
    "nextMYNetSales": 0,
    "unitId": 1,
    "weekEndingDate": "2018-05-31T00:00:00",
    "marketYear": 2018
  },
  {
    "commodityCode": 801,
    "countryCode": 2,
    "weeklyExports": 0,
    "accumulatedExports": 0,
    "outstandingSales": 3668800,
    "grossNewSales": 255500,
    "currentMYNetSales": 73500,
    "currentMYTotalCommitment": 3668800,
    "nextMYOutstandingSales": 3505500,
    "nextMYNetSales": 123000,
    "unitId": 1,
    "weekEndingDate": "2018-06-07T00:00:00",
    "marketYear": 2018
  },
  {
    "commodityCode": 801,
    "countryCode": 2,
    "weeklyExports": 0,
    "accumulatedExports": 0,
    "outstandingSales": 3464500,
    "grossNewSales": 162000,
    "currentMYNetSales": -204300,
    "currentMYTotalCommitment": 3464500,
    "nextMYOutstandingSales": 3677500,
    "nextMYNetSales": 172000,
    "unitId": 1,
    "weekEndingDate": "2018-06-14T00:00:00",
    "marketYear": 2018
  },
  {
    "commodityCode": 801,
    "countryCode": 2,
    "weeklyExports": 0,
    "accumulatedExports": 0,
    "outstandingSales": 3484250,
    "grossNewSales": 194750,
    "currentMYNetSales": 19750,
    "currentMYTotalCommitment": 3484250,
    "nextMYOutstandingSales": 3746500,
    "nextMYNetSales": 69000,
    "unitId": 1,
    "weekEndingDate": "2018-06-21T00:00:00",
    "marketYear": 2018
  },
  {
    "commodityCode": 801,
    "countryCode": 2,
    "weeklyExports": 0,
    "accumulatedExports": 0,
    "outstandingSales": 3532250,
    "grossNewSales": 390100,
    "currentMYNetSales": 48000,
    "currentMYTotalCommitment": 3532250,
    "nextMYOutstandingSales": 3934000,
    "nextMYNetSales": 187500,
    "unitId": 1,
    "weekEndingDate": "2018-06-28T00:00:00",
    "marketYear": 2018
  },
  {
    "commodityCode": 801,
    "countryCode": 2,
    "weeklyExports": 0,
    "accumulatedExports": 0,
    "outstandingSales": 3235400,
    "grossNewSales": 147150,
    "currentMYNetSales": -296850,
    "currentMYTotalCommitment": 3235400,
    "nextMYOutstandingSales": 4084500,
    "nextMYNetSales": 150500,
    "unitId": 1,
    "weekEndingDate": "2018-07-05T00:00:00",
    "marketYear": 2018
  },
  {
    "commodityCode": 801,
    "countryCode": 2,
    "weeklyExports": 0,
    "accumulatedExports": 0,
    "outstandingSales": 3122400,
    "grossNewSales": 106500,
    "currentMYNetSales": -113000,
    "currentMYTotalCommitment": 3122400,
    "nextMYOutstandingSales": 4517500,
    "nextMYNetSales": 433000,
    "unitId": 1,
    "weekEndingDate": "2018-07-12T00:00:00",
    "marketYear": 2018
  },
  {
    "commodityCode": 801,
    "countryCode": 2,
    "weeklyExports": 0,
    "accumulatedExports": 0,
    "outstandingSales": 2988400,
    "grossNewSales": 178000,
    "currentMYNetSales": -134000,
    "currentMYTotalCommitment": 2988400,
    "nextMYOutstandingSales": 4923700,
    "nextMYNetSales": 406200,
    "unitId": 1,
    "weekEndingDate": "2018-07-19T00:00:00",
    "marketYear": 2018
  },
  {
    "commodityCode": 801,
    "countryCode": 2,
    "weeklyExports": 0,
    "accumulatedExports": 0,
    "outstandingSales": 2672250,
    "grossNewSales": 88350,
    "currentMYNetSales": -316150,
    "currentMYTotalCommitment": 2672250,
    "nextMYOutstandingSales": 5335300,
    "nextMYNetSales": 411600,
    "unitId": 1,
    "weekEndingDate": "2018-07-26T00:00:00",
    "marketYear": 2018
  },
  {
    "commodityCode": 801,
    "countryCode": 2,
    "weeklyExports": 0,
    "accumulatedExports": 0,
    "outstandingSales": 2128750,
    "grossNewSales": 142000,
    "currentMYNetSales": -543500,
    "currentMYTotalCommitment": 2128750,
    "nextMYOutstandingSales": 5423450,
    "nextMYNetSales": 88150,
    "unitId": 1,
    "weekEndingDate": "2018-08-02T00:00:00",
    "marketYear": 2018
  },
  {
    "commodityCode": 801,
    "countryCode": 2,
    "weeklyExports": 0,
    "accumulatedExports": 0,
    "outstandingSales": 1923250,
    "grossNewSales": 80000,
    "currentMYNetSales": -205500,
    "currentMYTotalCommitment": 1923250,
    "nextMYOutstandingSales": 5796650,
    "nextMYNetSales": 373200,
    "unitId": 1,
    "weekEndingDate": "2018-08-09T00:00:00",
    "marketYear": 2018
  },
  {
    "commodityCode": 801,
    "countryCode": 2,
    "weeklyExports": 0,
    "accumulatedExports": 0,
    "outstandingSales": 1579400,
    "grossNewSales": 400,
    "currentMYNetSales": -343850,
    "currentMYTotalCommitment": 1579400,
    "nextMYOutstandingSales": 6156650,
    "nextMYNetSales": 360000,
    "unitId": 1,
    "weekEndingDate": "2018-08-16T00:00:00",
    "marketYear": 2018
  },
  {
    "commodityCode": 801,
    "countryCode": 2,
    "weeklyExports": 0,
    "accumulatedExports": 0,
    "outstandingSales": 1169800,
    "grossNewSales": 10900,
    "currentMYNetSales": -409600,
    "currentMYTotalCommitment": 1169800,
    "nextMYOutstandingSales": 6516850,
    "nextMYNetSales": 360200,
    "unitId": 1,
    "weekEndingDate": "2018-08-23T00:00:00",
    "marketYear": 2018
  },
  {
    "commodityCode": 801,
    "countryCode": 2,
    "weeklyExports": 0,
    "accumulatedExports": 0,
    "outstandingSales": 815400,
    "grossNewSales": 91300,
    "currentMYNetSales": -354400,
    "currentMYTotalCommitment": 815400,
    "nextMYOutstandingSales": 6940350,
    "nextMYNetSales": 423500,
    "unitId": 1,
    "weekEndingDate": "2018-08-30T00:00:00",
    "marketYear": 2018
  },
  {
    "commodityCode": 801,
    "countryCode": 2,
    "weeklyExports": 0,
    "accumulatedExports": 0,
    "outstandingSales": 799500,
    "grossNewSales": 0,
    "currentMYNetSales": -15900,
    "currentMYTotalCommitment": 799500,
    "nextMYOutstandingSales": 7566850,
    "nextMYNetSales": -173000,
    "unitId": 1,
    "weekEndingDate": "2018-09-06T00:00:00",
    "marketYear": 2018
  }
]