[
  {
    "commodityCode": 901,
    "countryCode": 1220,
    "weeklyExports": 9569,
    "accumulatedExports": 9569,
    "outstandingSales": 302980,
    "grossNewSales": 26503,
    "currentMYNetSales": 6690,
    "currentMYTotalCommitment": 312549,
    "nextMYOutstandingSales": 283,
    "nextMYNetSales": 0,
    "unitId": 1,
    "weekEndingDate": "2017-10-05T00:00:00",
    "marketYear": 2018
  },
  {
    "commodityCode": 901,
    "countryCode": 1220,
    "weeklyExports": 15142,
    "accumulatedExports": 24711,
    "outstandingSales": 311405,
    "grossNewSales": 23944,
    "currentMYNetSales": 23567,
    "currentMYTotalCommitment": 336116,
    "nextMYOutstandingSales": 283,
    "nextMYNetSales": 0,
    "unitId": 1,
    "weekEndingDate": "2017-10-12T00:00:00",
    "marketYear": 2018
  },
  {
    "commodityCode": 901,
    "countryCode": 1220,
    "weeklyExports": 17579,
    "accumulatedExports": 42290,
    "outstandingSales": 302430,
    "grossNewSales": 11276,
    "currentMYNetSales": 8604,
    "currentMYTotalCommitment": 344720,
    "nextMYOutstandingSales": 283,
    "nextMYNetSales": 0,
    "unitId": 1,
    "weekEndingDate": "2017-10-19T00:00:00",
    "marketYear": 2018
  },
  {
    "commodityCode": 901,
    "countryCode": 1220,
    "weeklyExports": 16960,
    "accumulatedExports": 59250,
    "outstandingSales": 302721,
    "grossNewSales": 17313,
    "currentMYNetSales": 17251,
    "currentMYTotalCommitment": 361971,
    "nextMYOutstandingSales": 283,
    "nextMYNetSales": 0,
    "unitId": 1,
    "weekEndingDate": "2017-10-26T00:00:00",
    "marketYear": 2018
  },
  {
    "commodityCode": 901,
    "countryCode": 1220,
    "weeklyExports": 17112,
    "accumulatedExports": 76362,
    "outstandingSales": 307988,
    "grossNewSales": 22907,
    "currentMYNetSales": 22379,
    "currentMYTotalCommitment": 384350,
    "nextMYOutstandingSales": 283,
    "nextMYNetSales": 0,
    "unitId": 1,
    "weekEndingDate": "2017-11-02T00:00:00",
    "marketYear": 2018
  },
  {
    "commodityCode": 901,
    "countryCode": 1220,
    "weeklyExports": 25313,
    "accumulatedExports": 101675,
    "outstandingSales": 288500,
    "grossNewSales": 5896,
    "currentMYNetSales": 5825,
    "currentMYTotalCommitment": 390175,
    "nextMYOutstandingSales": 6633,
    "nextMYNetSales": 6350,
    "unitId": 1,
    "weekEndingDate": "2017-11-09T00:00:00",
    "marketYear": 2018
  },
  {
    "commodityCode": 901,
    "countryCode": 1220,
    "weeklyExports": 15994,
    "accumulatedExports": 117669,
    "outstandingSales": 283707,
    "grossNewSales": 11202,
    "currentMYNetSales": 11201,
    "currentMYTotalCommitment": 401376,
    "nextMYOutstandingSales": 6633,
    "nextMYNetSales": 0,
    "unitId": 1,
    "weekEndingDate": "2017-11-16T00:00:00",
    "marketYear": 2018
  },
  {
    "commodityCode": 901,
    "countryCode": 1220,
    "weeklyExports": 17109,
    "accumulatedExports": 134778,
    "outstandingSales": 275596,
    "grossNewSales": 9001,
    "currentMYNetSales": 8998,
    "currentMYTotalCommitment": 410374,
    "nextMYOutstandingSales": 6633,
    "nextMYNetSales": 0,
    "unitId": 1,
    "weekEndingDate": "2017-11-23T00:00:00",
    "marketYear": 2018
  },
  {
    "commodityCode": 901,
    "countryCode": 1220,
    "weeklyExports": 14625,
    "accumulatedExports": 149403,
    "outstandingSales": 276175,
    "grossNewSales": 15952,
    "currentMYNetSales": 15204,
    "currentMYTotalCommitment": 425578,
    "nextMYOutstandingSales": 6633,
    "nextMYNetSales": 0,
    "unitId": 1,
    "weekEndingDate": "2017-11-30T00:00:00",
    "marketYear": 2018
  },
  {
    "commodityCode": 901,
    "countryCode": 1220,
    "weeklyExports": 25773,
    "accumulatedExports": 175176,
    "outstandingSales": 285395,
    "grossNewSales": 35015,
    "currentMYNetSales": 34993,
    "currentMYTotalCommitment": 460571,
    "nextMYOutstandingSales": 6633,
    "nextMYNetSales": 0,
    "unitId": 1,
    "weekEndingDate": "2017-12-07T00:00:00",
    "marketYear": 2018
  },
  {
    "commodityCode": 901,
    "countryCode": 1220,
    "weeklyExports": 26525,
    "accumulatedExports": 201701,
    "outstandingSales": 275952,
    "grossNewSales": 17083,
    "currentMYNetSales": 17082,
    "currentMYTotalCommitment": 477653,
    "nextMYOutstandingSales": 283,
    "nextMYNetSales": -6350,
    "unitId": 1,
    "weekEndingDate": "2017-12-14T00:00:00",
    "marketYear": 2018
  },
  {
    "commodityCode": 901,
    "countryCode": 1220,
    "weeklyExports": 15734,
    "accumulatedExports": 217435,
    "outstandingSales": 275973,
    "grossNewSales": 15755,
    "currentMYNetSales": 15755,
    "currentMYTotalCommitment": 493408,
    "nextMYOutstandingSales": 283,
    "nextMYNetSales": 0,
    "unitId": 1,
    "weekEndingDate": "2017-12-21T00:00:00",
    "marketYear": 2018
  },
  {
    "commodityCode": 901,
    "countryCode": 1220,
    "weeklyExports": 14590,
    "accumulatedExports": 232025,
    "outstandingSales": 275661,
    "grossNewSales": 14409,
    "currentMYNetSales": 14278,
    "currentMYTotalCommitment": 507686,
    "nextMYOutstandingSales": 283,
    "nextMYNetSales": 0,
    "unitId": 1,
    "weekEndingDate": "2017-12-28T00:00:00",
    "marketYear": 2018
  },
  {
    "commodityCode": 901,
    "countryCode": 1220,
    "weeklyExports": 16728,
    "accumulatedExports": 248753,
    "outstandingSales": 264957,
    "grossNewSales": 6707,
    "currentMYNetSales": 6024,
    "currentMYTotalCommitment": 513710,
    "nextMYOutstandingSales": 283,
    "nextMYNetSales": 0,
    "unitId": 1,
    "weekEndingDate": "2018-01-04T00:00:00",
    "marketYear": 2018
  },
  {
    "commodityCode": 901,
    "countryCode": 1220,
    "weeklyExports": 16261,
    "accumulatedExports": 265014,
    "outstandingSales": 256674,
    "grossNewSales": 7983,
    "currentMYNetSales": 7978,
    "currentMYTotalCommitment": 521688,
    "nextMYOutstandingSales": 260,
    "nextMYNetSales": -23,
    "unitId": 1,
    "weekEndingDate": "2018-01-11T00:00:00",
    "marketYear": 2018
  },
  {
    "commodityCode": 901,
    "countryCode": 1220,
    "weeklyExports": 17615,
    "accumulatedExports": 282629,
    "outstandingSales": 252411,
    "grossNewSales": 13478,
    "currentMYNetSales": 13352,
    "currentMYTotalCommitment": 535040,
    "nextMYOutstandingSales": 260,
    "nextMYNetSales": 0,
    "unitId": 1,
    "weekEndingDate": "2018-01-18T00:00:00",
    "marketYear": 2018
  },
  {
    "commodityCode": 901,
    "countryCode": 1220,
    "weeklyExports": 15968,
    "accumulatedExports": 298597,
    "outstandingSales": 240897,
    "grossNewSales": 4455,
    "currentMYNetSales": 4454,
    "currentMYTotalCommitment": 539494,
    "nextMYOutstandingSales": 377,
    "nextMYNetSales": 117,
    "unitId": 1,
    "weekEndingDate": "2018-01-25T00:00:00",
    "marketYear": 2018
  },
  {
    "commodityCode": 901,
    "countryCode": 1220,
    "weeklyExports": 16079,
    "accumulatedExports": 314676,
    "outstandingSales": 231253,
    "grossNewSales": 6620,
    "currentMYNetSales": 6435,
    "currentMYTotalCommitment": 545929,
    "nextMYOutstandingSales": 354,
    "nextMYNetSales": -23,
    "unitId": 1,
    "weekEndingDate": "2018-02-01T00:00:00",
    "marketYear": 2018
  },
  {
    "commodityCode": 901,
    "countryCode": 1220,
    "weeklyExports": 24039,
    "accumulatedExports": 338715,
    "outstandingSales": 215733,
    "grossNewSales": 8521,
    "currentMYNetSales": 8519,
    "currentMYTotalCommitment": 554448,
    "nextMYOutstandingSales": 354,
    "nextMYNetSales": 0,
    "unitId": 1,
    "weekEndingDate": "2018-02-08T00:00:00",
    "marketYear": 2018
  },
  {
    "commodityCode": 901,
    "countryCode": 1220,
    "weeklyExports": 15945,
    "accumulatedExports": 354660,
    "outstandingSales": 206659,
    "grossNewSales": 6886,
    "currentMYNetSales": 6871,
    "currentMYTotalCommitment": 561319,
    "nextMYOutstandingSales": 354,
    "nextMYNetSales": 0,
    "unitId": 1,
    "weekEndingDate": "2018-02-15T00:00:00",
    "marketYear": 2018
  },
  {
    "commodityCode": 901,
    "countryCode": 1220,
    "weeklyExports": 11702,
    "accumulatedExports": 366362,
    "outstandingSales": 197353,
    "grossNewSales": 2569,
    "currentMYNetSales": 2396,
    "currentMYTotalCommitment": 563715,
    "nextMYOutstandingSales": 354,
    "nextMYNetSales": 0,
    "unitId": 1,
    "weekEndingDate": "2018-02-22T00:00:00",
    "marketYear": 2018
  },
  {
    "commodityCode": 901,
    "countryCode": 1220,
    "weeklyExports": 17540,
    "accumulatedExports": 383902,
    "outstandingSales": 195601,
    "grossNewSales": 16057,
    "currentMYNetSales": 15788,
    "currentMYTotalCommitment": 579503,
    "nextMYOutstandingSales": 331,
    "nextMYNetSales": -23,
    "unitId": 1,
    "weekEndingDate": "2018-03-01T00:00:00",
    "marketYear": 2018
  },
  {
    "commodityCode": 901,
    "countryCode": 1220,
    "weeklyExports": 19176,
    "accumulatedExports": 403078,
    "outstandingSales": 181372,
    "grossNewSales": 4956,
    "currentMYNetSales": 4947,
    "currentMYTotalCommitment": 584450,
    "nextMYOutstandingSales": 331,
    "nextMYNetSales": 0,
    "unitId": 1,
    "weekEndingDate": "2018-03-08T00:00:00",
    "marketYear": 2018
  },
  {
    "commodityCode": 901,
    "countryCode": 1220,
    "weeklyExports": 13850,
    "accumulatedExports": 416928,
    "outstandingSales": 175104,
    "grossNewSales": 7604,
    "currentMYNetSales": 7582,
    "currentMYTotalCommitment": 592032,
    "nextMYOutstandingSales": 531,
    "nextMYNetSales": 200,
    "unitId": 1,
    "weekEndingDate": "2018-03-15T00:00:00",
    "marketYear": 2018
  },
  {
    "commodityCode": 901,
    "countryCode": 1220,
    "weeklyExports": 19029,
    "accumulatedExports": 435957,
    "outstandingSales": 168388,
    "grossNewSales": 12355,
    "currentMYNetSales": 12313,
    "currentMYTotalCommitment": 604345,
    "nextMYOutstandingSales": 531,
    "nextMYNetSales": 0,
    "unitId": 1,
    "weekEndingDate": "2018-03-22T00:00:00",
    "marketYear": 2018
  },
  {
    "commodityCode": 901,
    "countryCode": 1220,
    "weeklyExports": 13955,
    "accumulatedExports": 449912,
    "outstandingSales": 168596,
    "grossNewSales": 14288,
    "currentMYNetSales": 14163,
    "currentMYTotalCommitment": 618508,
    "nextMYOutstandingSales": 531,
    "nextMYNetSales": 0,
    "unitId": 1,
    "weekEndingDate": "2018-03-29T00:00:00",
    "marketYear": 2018
  },
  {
    "commodityCode": 901,
    "countryCode": 1220,
    "weeklyExports": 15529,
    "accumulatedExports": 465441,
    "outstandingSales": 162091,
    "grossNewSales": 9024,
    "currentMYNetSales": 9024,
    "currentMYTotalCommitment": 627532,
    "nextMYOutstandingSales": 551,
    "nextMYNetSales": 20,
    "unitId": 1,
    "weekEndingDate": "2018-04-05T00:00:00",
    "marketYear": 2018
  },
  {
    "commodityCode": 901,
    "countryCode": 1220,
    "weeklyExports": 15220,
    "accumulatedExports": 480661,
    "outstandingSales": 153588,
    "grossNewSales": 6739,
    "currentMYNetSales": 6717,
    "currentMYTotalCommitment": 634249,
    "nextMYOutstandingSales": 508,
    "nextMYNetSales": -43,
    "unitId": 1,
    "weekEndingDate": "2018-04-12T00:00:00",
    "marketYear": 2018
  },
  {
    "commodityCode": 901,
    "countryCode": 1220,
    "weeklyExports": 14183,
    "accumulatedExports": 494844,
    "outstandingSales": 160535,
    "grossNewSales": 21315,
    "currentMYNetSales": 21130,
    "currentMYTotalCommitment": 655379,
    "nextMYOutstandingSales": 1357,
    "nextMYNetSales": 849,
    "unitId": 1,
    "weekEndingDate": "2018-04-19T00:00:00",
    "marketYear": 2018
  },
  {
    "commodityCode": 901,
    "countryCode": 1220,
    "weeklyExports": 14692,
    "accumulatedExports": 509536,
    "outstandingSales": 165561,
    "grossNewSales": 20563,
    "currentMYNetSales": 19718,
    "currentMYTotalCommitment": 675097,
    "nextMYOutstandingSales": 1357,
    "nextMYNetSales": 0,
    "unitId": 1,
    "weekEndingDate": "2018-04-26T00:00:00",
    "marketYear": 2018
  },
  {
    "commodityCode": 901,
    "countryCode": 1220,
    "weeklyExports": 11023,
    "accumulatedExports": 520559,
    "outstandingSales": 156821,
    "grossNewSales": 2437,
    "currentMYNetSales": 2283,
    "currentMYTotalCommitment": 677380,
    "nextMYOutstandingSales": 1357,
    "nextMYNetSales": 0,
    "unitId": 1,
    "weekEndingDate": "2018-05-03T00:00:00",
    "marketYear": 2018
  },
  {
    "commodityCode": 901,
    "countryCode": 1220,
    "weeklyExports": 12132,
    "accumulatedExports": 532691,
    "outstandingSales": 162162,
    "grossNewSales": 17474,
    "currentMYNetSales": 17473,
    "currentMYTotalCommitment": 694853,
    "nextMYOutstandingSales": 2023,
    "nextMYNetSales": 666,
    "unitId": 1,
    "weekEndingDate": "2018-05-10T00:00:00",
    "marketYear": 2018
  },
  {
    "commodityCode": 901,
    "countryCode": 1220,
    "weeklyExports": 18928,
    "accumulatedExports": 551619,
    "outstandingSales": 168943,
    "grossNewSales": 26024,
    "currentMYNetSales": 25709,
    "currentMYTotalCommitment": 720562,
    "nextMYOutstandingSales": 3021,
    "nextMYNetSales": 998,
    "unitId": 1,
    "weekEndingDate": "2018-05-17T00:00:00",
    "marketYear": 2018
  },
  {
    "commodityCode": 901,
    "countryCode": 1220,
    "weeklyExports": 17073,
    "accumulatedExports": 568692,
    "outstandingSales": 163366,
    "grossNewSales": 11606,
    "currentMYNetSales": 11496,
    "currentMYTotalCommitment": 732058,
    "nextMYOutstandingSales": 3221,
    "nextMYNetSales": 200,
    "unitId": 1,
    "weekEndingDate": "2018-05-24T00:00:00",
    "marketYear": 2018
  },
  {
    "commodityCode": 901,
    "countryCode": 1220,
    "weeklyExports": 14006,
    "accumulatedExports": 582698,
    "outstandingSales": 163021,
    "grossNewSales": 14236,
    "currentMYNetSales": 13661,
    "currentMYTotalCommitment": 745719,
    "nextMYOutstandingSales": 3221,
    "nextMYNetSales": 0,
    "unitId": 1,
    "weekEndingDate": "2018-05-31T00:00:00",
    "marketYear": 2018
  },
  {
    "commodityCode": 901,
    "countryCode": 1220,
    "weeklyExports": 23997,
    "accumulatedExports": 606695,
    "outstandingSales": 146632,
    "grossNewSales": 7736,
    "currentMYNetSales": 7608,
    "currentMYTotalCommitment": 753327,
    "nextMYOutstandingSales": 3197,
    "nextMYNetSales": -24,
    "unitId": 1,
    "weekEndingDate": "2018-06-07T00:00:00",
    "marketYear": 2018
  },
  {
    "commodityCode": 901,
    "countryCode": 1220,
    "weeklyExports": 18886,
    "accumulatedExports": 625581,
    "outstandingSales": 140434,
    "grossNewSales": 12728,
    "currentMYNetSales": 12688,
    "currentMYTotalCommitment": 766015,
    "nextMYOutstandingSales": 3197,
    "nextMYNetSales": 0,
    "unitId": 1,
    "weekEndingDate": "2018-06-14T00:00:00",
    "marketYear": 2018
  },
  {
    "commodityCode": 901,
    "countryCode": 1220,
    "weeklyExports": 18975,
    "accumulatedExports": 644556,
    "outstandingSales": 148085,
    "grossNewSales": 26637,
    "currentMYNetSales": 26626,
    "currentMYTotalCommitment": 792641,
    "nextMYOutstandingSales": 7442,
    "nextMYNetSales": 4245,
    "unitId": 1,
    "weekEndingDate": "2018-06-21T00:00:00",
    "marketYear": 2018
  },
  {
    "commodityCode": 901,
    "countryCode": 1220,
    "weeklyExports": 19061,
    "accumulatedExports": 663617,
    "outstandingSales": 139101,
    "grossNewSales": 10083,
    "currentMYNetSales": 10077,
    "currentMYTotalCommitment": 802718,
    "nextMYOutstandingSales": 11194,
    "nextMYNetSales": 3752,
    "unitId": 1,
    "weekEndingDate": "2018-06-28T00:00:00",
    "marketYear": 2018
  },
  {
    "commodityCode": 901,
    "countryCode": 1220,
    "weeklyExports": 17609,
    "accumulatedExports": 681226,
    "outstandingSales": 128600,
    "grossNewSales": 7120,
    "currentMYNetSales": 7108,
    "currentMYTotalCommitment": 809826,
    "nextMYOutstandingSales": 12072,
    "nextMYNetSales": 878,
    "unitId": 1,
    "weekEndingDate": "2018-07-05T00:00:00",
    "marketYear": 2018
  },
  {
    "commodityCode": 901,
    "countryCode": 1220,
    "weeklyExports": 16966,
    "accumulatedExports": 698192,
    "outstandingSales": 120076,
    "grossNewSales": 8465,
    "currentMYNetSales": 8442,
    "currentMYTotalCommitment": 818268,
    "nextMYOutstandingSales": 12768,
    "nextMYNetSales": 696,
    "unitId": 1,
    "weekEndingDate": "2018-07-12T00:00:00",
    "marketYear": 2018
  },
  {
    "commodityCode": 901,
    "countryCode": 1220,
    "weeklyExports": 12436,
    "accumulatedExports": 710628,
    "outstandingSales": 115337,
    "grossNewSales": 7697,
    "currentMYNetSales": 7697,
    "currentMYTotalCommitment": 825965,
    "nextMYOutstandingSales": 13908,
    "nextMYNetSales": 1140,
    "unitId": 1,
    "weekEndingDate": "2018-07-19T00:00:00",
    "marketYear": 2018
  },
  {
    "commodityCode": 901,
    "countryCode": 1220,
    "weeklyExports": 14253,
    "accumulatedExports": 724881,
    "outstandingSales": 106546,
    "grossNewSales": 8884,
    "currentMYNetSales": 5462,
    "currentMYTotalCommitment": 831427,
    "nextMYOutstandingSales": 13908,
    "nextMYNetSales": 0,
    "unitId": 1,
    "weekEndingDate": "2018-07-26T00:00:00",
    "marketYear": 2018
  },
  {
    "commodityCode": 901,
    "countryCode": 1220,
    "weeklyExports": 15674,
    "accumulatedExports": 740555,
    "outstandingSales": 102477,
    "grossNewSales": 11716,
    "currentMYNetSales": 11605,
    "currentMYTotalCommitment": 843032,
    "nextMYOutstandingSales": 13988,
    "nextMYNetSales": 80,
    "unitId": 1,
    "weekEndingDate": "2018-08-02T00:00:00",
    "marketYear": 2018
  },
  {
    "commodityCode": 901,
    "countryCode": 1220,
    "weeklyExports": 12821,
    "accumulatedExports": 753376,
    "outstandingSales": 98785,
    "grossNewSales": 9129,
    "currentMYNetSales": 9129,
    "currentMYTotalCommitment": 852161,
    "nextMYOutstandingSales": 19486,
    "nextMYNetSales": 5498,
    "unitId": 1,
    "weekEndingDate": "2018-08-09T00:00:00",
    "marketYear": 2018
  },
  {
    "commodityCode": 901,
    "countryCode": 1220,
    "weeklyExports": 10691,
    "accumulatedExports": 764067,
    "outstandingSales": 98681,
    "grossNewSales": 10564,
    "currentMYNetSales": 10587,
    "currentMYTotalCommitment": 862748,
    "nextMYOutstandingSales": 25932,
    "nextMYNetSales": 6446,
    "unitId": 1,
    "weekEndingDate": "2018-08-16T00:00:00",
    "marketYear": 2018
  },
  {
    "commodityCode": 901,
    "countryCode": 1220,
    "weeklyExports": 15524,
    "accumulatedExports": 779591,
    "outstandingSales": 90540,
    "grossNewSales": 7409,
    "currentMYNetSales": 7383,
    "currentMYTotalCommitment": 870131,
    "nextMYOutstandingSales": 26883,
    "nextMYNetSales": 951,
    "unitId": 1,
    "weekEndingDate": "2018-08-23T00:00:00",
    "marketYear": 2018
  },
  {
    "commodityCode": 901,
    "countryCode": 1220,
    "weeklyExports": 12581,
    "accumulatedExports": 792172,
    "outstandingSales": 89633,
    "grossNewSales": 12323,
    "currentMYNetSales": 11674,
    "currentMYTotalCommitment": 881805,
    "nextMYOutstandingSales": 64486,
    "nextMYNetSales": 37603,
    "unitId": 1,
    "weekEndingDate": "2018-08-30T00:00:00",
    "marketYear": 2018
  },
  {
    "commodityCode": 901,
    "countryCode": 1220,
    "weeklyExports": 21172,
    "accumulatedExports": 813344,
    "outstandingSales": 76994,
    "grossNewSales": 8556,
    "currentMYNetSales": 8533,
    "currentMYTotalCommitment": 890338,
    "nextMYOutstandingSales": 69741,
    "nextMYNetSales": 5255,
    "unitId": 1,
    "weekEndingDate": "2018-09-06T00:00:00",
    "marketYear": 2018
  },
  {
    "commodityCode": 901,
    "countryCode": 1220,
    "weeklyExports": 20639,
    "accumulatedExports": 833983,
    "outstandingSales": 68657,
    "grossNewSales": 12302,
    "currentMYNetSales": 12302,
    "currentMYTotalCommitment": 902640,
    "nextMYOutstandingSales": 80551,
    "nextMYNetSales": 10810,
    "unitId": 1,
    "weekEndingDate": "2018-09-13T00:00:00",
    "marketYear": 2018
  },
  {
    "commodityCode": 901,
    "countryCode": 1220,
    "weeklyExports": 26124,
    "accumulatedExports": 860107,
    "outstandingSales": 60381,
    "grossNewSales": 17863,
    "currentMYNetSales": 17848,
    "currentMYTotalCommitment": 920488,
    "nextMYOutstandingSales": 118128,
    "nextMYNetSales": 37577,
    "unitId": 1,
    "weekEndingDate": "2018-09-20T00:00:00",
    "marketYear": 2018
  },
  {
    "commodityCode": 901,
    "countryCode": 1220,
    "weeklyExports": 16966,
    "accumulatedExports": 877073,
    "outstandingSales": 49221,
    "grossNewSales": 7015,
    "currentMYNetSales": 5806,
    "currentMYTotalCommitment": 926294,
    "nextMYOutstandingSales": 137344,
    "nextMYNetSales": 19216,
    "unitId": 1,
    "weekEndingDate": "2018-09-27T00:00:00",
    "marketYear": 2018
  },
  {
    "commodityCode": 901,
    "countryCode": 1220,
    "weeklyExports": 5900,
    "accumulatedExports": 882973,
    "outstandingSales": 55232,
    "grossNewSales": 12527,
    "currentMYNetSales": 11911,
    "currentMYTotalCommitment": 938205,
    "nextMYOutstandingSales": 250695,
    "nextMYNetSales": 71218,
    "unitId": 1,
    "weekEndingDate": "2018-10-04T00:00:00",
    "marketYear": 2018
  }
]